{
  "city": "Tokyo",
  "latitude": 35.6895,
  "longitude": 139.6917,
  "temperature_celsius": 6.09,
  "condition": "Rain",
  "condition_description": "moderate rain",
  "icon_code": "10n",
  "temp_min_celsius": 4.77,
  "temp_max_celsius": 7.01,
  "humidity": 59,
  "feels_like_celsius": 5.14,
  "pressure": 1013,
  "visibility": 10000,
  "wind_deg": 290,
  "gust_speed": ,
  "wind_speed": 1.54,
  "rainfall_mm": 71.62,
  "snowfall_mm": ,
  "clouds": 75,
  "sunrise_readable": "2025-01-20 04:48:39",
  "sunset_readable": "2025-01-20 14:55:18",
  "timezone": 32400,
  "coord_lon": 139.6917,
  "coord_lat": 35.6895,
  "wind_direction_text": "West-Northwest",
  "weather_description_with_wind": "Wind Direction: West-Northwest",
  "forecast_24h": [          {
            "temperature_celsius": 6.09,
            "condition": "Clouds",
            "icon_code": "04n",
            "date_readable": "04:00"
          },          {
            "temperature_celsius": 6.95,
            "condition": "Clouds",
            "icon_code": "04d",
            "date_readable": "07:00"
          },          {
            "temperature_celsius": 9.10,
            "condition": "Clouds",
            "icon_code": "04d",
            "date_readable": "10:00"
          },          {
            "temperature_celsius": 11.98,
            "condition": "Clouds",
            "icon_code": "04d",
            "date_readable": "13:00"
          },          {
            "temperature_celsius": 11.82,
            "condition": "Clouds",
            "icon_code": "04n",
            "date_readable": "16:00"
          },          {
            "temperature_celsius": 10.61,
            "condition": "Clouds",
            "icon_code": "04n",
            "date_readable": "19:00"
          },          {
            "temperature_celsius": 9.79,
            "condition": "Clouds",
            "icon_code": "04n",
            "date_readable": "22:00"
          },          {
            "temperature_celsius": 8.69,
            "condition": "Clouds",
            "icon_code": "04n",
            "date_readable": "01:00"
          },
  ]
}

