{
  "city": "Tokyo",
  "latitude": 35.6895,
  "longitude": 139.6917,
  "temperature_celsius": 5.71,
  "condition": "Mist",
  "condition_description": "mist",
  "icon_code": "50d",
  "temp_min_celsius": 4.75,
  "temp_max_celsius": 6.79,
  "humidity": 89,
  "feels_like_celsius": .33,
  "pressure": 1015,
  "visibility": 5000,
  "wind_deg": 20,
  "gust_speed": ,
  "wind_speed": 10.8,
  "rainfall_mm": 92.71,
  "snowfall_mm": ,
  "clouds": 75,
  "sunrise_readable": "2025-03-03 04:09:13",
  "sunset_readable": "2025-03-03 15:37:35",
  "timezone": 32400,
  "coord_lon": 139.6917,
  "coord_lat": 35.6895,
  "wind_direction_text": "North-Northeast",
  "weather_description_with_wind": "Wind Direction: North-Northeast",
  "forecast_24h": [          {
            "temperature_celsius": 5.71,
            "condition": "Snow",
            "icon_code": "13d",
            "date_readable": "10:00"
          },          {
            "temperature_celsius": 4.58,
            "condition": "Snow",
            "icon_code": "13d",
            "date_readable": "13:00"
          },          {
            "temperature_celsius": 3.82,
            "condition": "Snow",
            "icon_code": "13n",
            "date_readable": "16:00"
          },          {
            "temperature_celsius": 4.10,
            "condition": "Clouds",
            "icon_code": "04n",
            "date_readable": "19:00"
          },          {
            "temperature_celsius": 4.26,
            "condition": "Clouds",
            "icon_code": "04n",
            "date_readable": "22:00"
          },          {
            "temperature_celsius": 3.94,
            "condition": "Clouds",
            "icon_code": "04n",
            "date_readable": "01:00"
          },          {
            "temperature_celsius": 3.61,
            "condition": "Clouds",
            "icon_code": "04n",
            "date_readable": "04:00"
          },          {
            "temperature_celsius": 4.67,
            "condition": "Clouds",
            "icon_code": "04d",
            "date_readable": "07:00"
          },
  ]
}

