{
  "city": "Tokyo",
  "latitude": 35.6895,
  "longitude": 139.6917,
  "temperature_celsius": 11.66,
  "condition": "Clear",
  "condition_description": "clear sky",
  "icon_code": "01n",
  "temp_min_celsius": 10.79,
  "temp_max_celsius": 12.02,
  "humidity": 68,
  "feels_like_celsius": 10.66,
  "pressure": 1013,
  "visibility": 10000,
  "wind_deg": 0,
  "gust_speed": ,
  "wind_speed": 1.03,
  "rainfall_mm": ,
  "snowfall_mm": ,
  "clouds": 0,
  "sunrise_readable": "2025-11-14 04:15:50",
  "sunset_readable": "2025-11-14 14:35:36",
  "timezone": 32400,
  "coord_lon": 139.6917,
  "coord_lat": 35.6895,
  "wind_direction_text": "North",
  "weather_description_with_wind": "Wind Direction: North",
  "forecast_24h": [          {
            "temperature_celsius": 11.41,
            "condition": "Clear",
            "icon_code": "01n",
            "date_readable": "01:00"
          },          {
            "temperature_celsius": 12.09,
            "condition": "Clouds",
            "icon_code": "02n",
            "date_readable": "04:00"
          },          {
            "temperature_celsius": 13.90,
            "condition": "Clouds",
            "icon_code": "02d",
            "date_readable": "07:00"
          },          {
            "temperature_celsius": 17.44,
            "condition": "Clear",
            "icon_code": "01d",
            "date_readable": "10:00"
          },          {
            "temperature_celsius": 18.41,
            "condition": "Clouds",
            "icon_code": "02d",
            "date_readable": "13:00"
          },          {
            "temperature_celsius": 16.66,
            "condition": "Rain",
            "icon_code": "10n",
            "date_readable": "16:00"
          },          {
            "temperature_celsius": 15.69,
            "condition": "Rain",
            "icon_code": "10n",
            "date_readable": "19:00"
          },          {
            "temperature_celsius": 15.26,
            "condition": "Rain",
            "icon_code": "10n",
            "date_readable": "22:00"
          },
  ]
}

