{
  "city": "Tokyo",
  "latitude": 35.6895,
  "longitude": 139.6917,
  "temperature_celsius": 17.94,
  "condition": "Clear",
  "condition_description": "clear sky",
  "icon_code": "01d",
  "temp_min_celsius": 16.45,
  "temp_max_celsius": 19.23,
  "humidity": 95,
  "feels_like_celsius": 18.27,
  "pressure": 1005,
  "visibility": 10000,
  "wind_deg": 300,
  "gust_speed": ,
  "wind_speed": 1.03,
  "rainfall_mm": ,
  "snowfall_mm": ,
  "clouds": 0,
  "sunrise_readable": "2024-06-19 02:25:20",
  "sunset_readable": "2024-06-19 16:59:48",
  "timezone": 32400,
  "coord_lon": 139.6917,
  "coord_lat": 35.6895,
  "wind_direction_text": "West-Northwest",
  "weather_description_with_wind": "Wind Direction: West-Northwest",
  "forecast_24h": [          {
            "temperature_celsius": 17.94,
            "condition": "Clear",
            "icon_code": "01d",
            "date_readable": "04:00"
          },          {
            "temperature_celsius": 20.15,
            "condition": "Clear",
            "icon_code": "01d",
            "date_readable": "07:00"
          },          {
            "temperature_celsius": 24.43,
            "condition": "Clear",
            "icon_code": "01d",
            "date_readable": "10:00"
          },          {
            "temperature_celsius": 29.31,
            "condition": "Clear",
            "icon_code": "01d",
            "date_readable": "13:00"
          },          {
            "temperature_celsius": 26.22,
            "condition": "Clouds",
            "icon_code": "04d",
            "date_readable": "16:00"
          },          {
            "temperature_celsius": 24.00,
            "condition": "Clouds",
            "icon_code": "04n",
            "date_readable": "19:00"
          },          {
            "temperature_celsius": 22.94,
            "condition": "Clouds",
            "icon_code": "03n",
            "date_readable": "22:00"
          },          {
            "temperature_celsius": 22.24,
            "condition": "Clouds",
            "icon_code": "02n",
            "date_readable": "01:00"
          },
  ]
}

